oppoudpsdk/__init__.py
oppoudpsdk/async_helpers.py
oppoudpsdk/client.py
oppoudpsdk/codes.py
oppoudpsdk/const.py
oppoudpsdk/device.py
oppoudpsdk/exceptions.py
oppoudpsdk/helpers.py
oppoudpsdk/states.py
oppoudpsdk/command/__init__.py
oppoudpsdk/command/command.py
oppoudpsdk/command/enums.py
oppoudpsdk/command/query_command.py
oppoudpsdk/command/remote_command.py
oppoudpsdk/command/set_command.py
oppoudpsdk/response/__init__.py
oppoudpsdk/response/enums.py
oppoudpsdk/response/factory.py
oppoudpsdk/response/mapping.py
oppoudpsdk/response/mutator.py
oppoudpsdk/response/response.py
oppoudpsdk-0.1.19.dist-info/LICENSE
oppoudpsdk-0.1.19.dist-info/METADATA
oppoudpsdk-0.1.19.dist-info/WHEEL
oppoudpsdk-0.1.19.dist-info/top_level.txt
oppoudpsdk-0.1.19.dist-info/RECORD
