Metadata-Version: 2.1
Name: oppoudpsdk
Version: 0.1.19
Summary: Python SDK for Oppo UDP Devices
Home-page: https://github.com/simbaja/oppoudpsdk
Author: Jack Simbach
Author-email: jack.simbach@gmail.com
License: MIT
Classifier: License :: OSI Approved :: MIT License
Classifier: Programming Language :: Python :: 3
Classifier: Programming Language :: Python :: 3.7
License-File: LICENSE
Requires-Dist: magicattr
